Metadata-Version: 1.0
Name: lib-fabric-dreamhost
Version: 0.0.1
Summary: Lib with shared Fabric tasks to be used with Dreamhost.
Home-page: https://bitbucket.org/fernandoe/lib-fabric-dreamhost
Author: Fernando Espíndola
Author-email: fer.esp@gmail.com
License: MIT
Platform: UNKNOWN
